src/__init__.py
src/__main__.py
src/twopasswords.py
src/config/__init__.py
src/config/config.yaml.example
src/config/config_loader.py
src/config/words.txt
src/utils/__init__.py
src/utils/database.py
src/utils/emailer.py
src/utils/facescan.py
src/utils/password_generator.py
src/views/__init__.py
src/views/tui_auth.py
src/views/tui_first_run.py
src/views/tui_main.py
src/views/tui_selector.py
twopasswords-0.0.14.dist-info/LICENSE
twopasswords-0.0.14.dist-info/METADATA
twopasswords-0.0.14.dist-info/WHEEL
twopasswords-0.0.14.dist-info/entry_points.txt
twopasswords-0.0.14.dist-info/top_level.txt
twopasswords-0.0.14.dist-info/RECORD
