Metadata-Version: 2.1
Name: twopasswords
Version: 0.0.14
Summary: Password manager with face recognition
Home-page: https://github.com/gennadis/twopasswords
Author: Gennady Badinov
Author-email: gennady.badinov@gmail.com
License: MIT
Platform: UNKNOWN
Classifier: Topic :: Security
Classifier: Topic :: Security :: Cryptography
Classifier: License :: OSI Approved :: MIT License
Classifier: Operating System :: MacOS
Classifier: Operating System :: POSIX :: Linux
Classifier: Natural Language :: English
Classifier: Programming Language :: Python :: 3
Classifier: Programming Language :: Python
Classifier: Development Status :: 3 - Alpha
License-File: LICENSE
Requires-Dist: cmake
Requires-Dist: py-cui
Requires-Dist: opencv-python
Requires-Dist: face-recognition
Requires-Dist: sqlcipher3 (==0.4.5)
Requires-Dist: pyperclip
Requires-Dist: PyYAML
Requires-Dist: Faker
